LICENSE
MANIFEST.in
README.rst
setup.cfg
setup.py
src/yass/__init__.py
src/yass/command_line.py
src/yass/geometry.py
src/yass/mfm.py
src/yass/pipeline.py
src/yass/util.py
src/yass/assets/config/schema.yaml
src/yass/assets/logger/config.yaml
src/yass/assets/models/.DS_Store
src/yass/assets/models/ae_nn1.ckpt.data-00000-of-00001
src/yass/assets/models/ae_nn1.ckpt.index
src/yass/assets/models/ae_nn1.ckpt.meta
src/yass/assets/models/ae_nn1.yaml
src/yass/assets/models/detect_nn1.ckpt.data-00000-of-00001
src/yass/assets/models/detect_nn1.ckpt.index
src/yass/assets/models/detect_nn1.ckpt.meta
src/yass/assets/models/detect_nn1.yaml
src/yass/assets/models/triage_nn1.ckpt.data-00000-of-00001
src/yass/assets/models/triage_nn1.ckpt.index
src/yass/assets/models/triage_nn1.ckpt.meta
src/yass/assets/models/triage_nn1.yaml
src/yass/assets/phy/params.py
src/yass/augment/__init__.py
src/yass/augment/choose.py
src/yass/augment/crop.py
src/yass/augment/make.py
src/yass/augment/noise.py
src/yass/augment/train_ae.py
src/yass/augment/train_all.py
src/yass/augment/train_detector.py
src/yass/augment/train_triage.py
src/yass/augment/util.py
src/yass/batch/__init__.py
src/yass/batch/batch.py
src/yass/batch/buffer.py
src/yass/batch/generator.py
src/yass/batch/pipeline.py
src/yass/batch/reader.py
src/yass/batch/util.py
src/yass/batch/vectorize.py
src/yass/cluster/__init__.py
src/yass/cluster/coreset.py
src/yass/cluster/mask.py
src/yass/cluster/run.py
src/yass/cluster/subsample.py
src/yass/cluster/triage.py
src/yass/cluster/util.py
src/yass/config/__init__.py
src/yass/config/config.py
src/yass/config/validate.py
src/yass/deconvolute/__init__.py
src/yass/deconvolute/deconvolve.py
src/yass/deconvolute/match.py
src/yass/deconvolute/run.py
src/yass/deconvolute/util.py
src/yass/detect/__init__.py
src/yass/detect/run.py
src/yass/evaluate/__init__.py
src/yass/evaluate/analyzer.py
src/yass/evaluate/stability.py
src/yass/evaluate/stability_filters.py
src/yass/evaluate/util.py
src/yass_algorithm.egg-info/PKG-INFO
src/yass_algorithm.egg-info/SOURCES.txt
src/yass_algorithm.egg-info/dependency_links.txt
src/yass_algorithm.egg-info/entry_points.txt
src/yass_algorithm.egg-info/not-zip-safe
src/yass_algorithm.egg-info/requires.txt
src/yass_algorithm.egg-info/top_level.txt