Metadata-Version: 2.1
Name: yass-algorithm
Version: 0.9
Summary: YASS: Yet Another Spike Sorter
Home-page: https://github.com/paninski-lab/yass
Author: Peter Lee, Eduardo Blancas
Author-email: fkq8@blancas.io
License: Apache
Download-URL: https://github.com/paninski-lab/yass/archive/0.9.tar.gz
Platform: UNKNOWN
Classifier: License :: OSI Approved :: Apache Software License
Classifier: Programming Language :: Python
Classifier: Programming Language :: Python :: 2.7
Classifier: Programming Language :: Python :: 3
Classifier: Programming Language :: Python :: 3.3
Classifier: Programming Language :: Python :: 3.4
Classifier: Programming Language :: Python :: 3.5
Classifier: Programming Language :: Python :: 3.6
Classifier: Programming Language :: Python :: Implementation :: CPython
Provides-Extra: tensorflow
